src/__init__.py
src/log.py
src/test.py
logging_r-0.0.2.dist-info/LICENSE
logging_r-0.0.2.dist-info/METADATA
logging_r-0.0.2.dist-info/WHEEL
logging_r-0.0.2.dist-info/top_level.txt
logging_r-0.0.2.dist-info/RECORD
